easy_flags/__init__.py
easy_flags/base.py
easy_flags/errors.py
easy_flags/fields.py
easy_flags-0.2.1.dist-info/DESCRIPTION.rst
easy_flags-0.2.1.dist-info/METADATA
easy_flags-0.2.1.dist-info/RECORD
easy_flags-0.2.1.dist-info/WHEEL
easy_flags-0.2.1.dist-info/metadata.json
easy_flags-0.2.1.dist-info/top_level.txt
