Metadata-Version: 2.0
Name: easy-flags
Version: 0.2.1
Summary: Simplified flags definition.
Home-page: https://github.com/vaniakosmos/easy_flags
Author: Bachynin Ivan
Author-email: bachynin.i@gmail.com
License: MIT
Keywords: flags,argparse
Platform: UNKNOWN
Classifier: Development Status :: 4 - Beta
Classifier: Intended Audience :: Developers
Classifier: License :: OSI Approved :: MIT License
Classifier: Programming Language :: Python
Classifier: Programming Language :: Python :: 3.5
Classifier: Programming Language :: Python :: 3.6
Classifier: Programming Language :: Python :: Implementation :: CPython
Classifier: Topic :: Utilities
